colorsysx/__init__.py
colorsysx/_glhs.py
colorsysx/_hcy.py
colorsysx/_helpers.py
colorsysx/_swizzle.py
colorsysx/_yiq.py
colorsysx/_yuv.py
colorsysx/weights.py
colorsysx-1.1.dist-info/LICENSE
colorsysx-1.1.dist-info/WHEEL
colorsysx-1.1.dist-info/METADATA
colorsysx-1.1.dist-info/RECORD
