Metadata-Version: 2.1
Name: colorsysx
Version: 1.1
Summary: Extra, human-relevant, colour spaces derived from RGB.
Author-email: Andrew Chadwick <a.t.chadwick@gmail.com>
Requires-Python: >=3.9
Classifier: Development Status :: 4 - Beta
Classifier: License :: OSI Approved :: MIT License
Classifier: Topic :: Multimedia :: Graphics :: Presentation
Classifier: Topic :: Software Development :: Libraries
Classifier: Intended Audience :: Developers
Classifier: Programming Language :: Python :: 3 :: Only
Requires-Dist: pytest >=7,<8 ; extra == "dev"
Requires-Dist: flake8 >=6,<7 ; extra == "dev"
Requires-Dist: pip-tools ; extra == "dev"
Requires-Dist: pip-sync-faster ; extra == "dev"
Requires-Dist: ptpython ; extra == "dev"
Provides-Extra: dev
